sciencelogic/presentations.py
sciencelogic/performance_data.py
sciencelogic/device.py
sciencelogic/client.py
sciencelogic/__init__.py
sciencelogic-0.6.0.dist-info/RECORD
sciencelogic-0.6.0.dist-info/metadata.json
sciencelogic-0.6.0.dist-info/WHEEL
sciencelogic-0.6.0.dist-info/DESCRIPTION.rst
sciencelogic-0.6.0.dist-info/top_level.txt
sciencelogic-0.6.0.dist-info/METADATA
