Metadata-Version: 2.0
Name: sciencelogic
Version: 0.6.0
Summary: Client library for sciencelogic EM7
Home-page: https://github.com/tonybaloney/sciencelogic
Author: Anthony Shaw
Author-email: anthonyshaw@apache.org
License: MIT
Keywords: sciencelogic
Platform: UNKNOWN
Classifier: Development Status :: 2 - Pre-Alpha
Classifier: Intended Audience :: Developers
Classifier: License :: OSI Approved :: MIT License
Classifier: Natural Language :: English
Classifier: Programming Language :: Python :: 2
Classifier: Programming Language :: Python :: 2.6
Classifier: Programming Language :: Python :: 2.7
Classifier: Programming Language :: Python :: 3
Classifier: Programming Language :: Python :: 3.3
Classifier: Programming Language :: Python :: 3.4
Classifier: Programming Language :: Python :: 3.5
Requires-Dist: requests
Requires-Dist: pyyaml
